simpleindex/__init__.py
simpleindex/__main__.py
simpleindex/configs.py
simpleindex/routes.py
simpleindex-0.6.3.dist-info/entry_points.txt
simpleindex-0.6.3.dist-info/LICENSE
simpleindex-0.6.3.dist-info/WHEEL
simpleindex-0.6.3.dist-info/METADATA
simpleindex-0.6.3.dist-info/RECORD
